snowpyt/CAAMLv6_xml.py
snowpyt/JC_pit_class.py
snowpyt/__init__.py
snowpyt/__version__.py
snowpyt/pit_class.py
snowpyt/data_example/201902261050_marsh_ørjan.caaml
snowpyt/data_example/20190228_finse_isotopes.csv
snowpyt/snowflake/__init__.py
snowpyt/snowflake/basal_ice.png
snowpyt/snowflake/cavity_crevasse_hoar.png
snowpyt/snowflake/chains_of_depth_hoar.png
snowpyt/snowflake/cluster_rounded.png
snowpyt/snowflake/faceted.png
snowpyt/snowflake/faceted_rounded.png
snowpyt/snowflake/hollow_cups.png
snowpyt/snowflake/hollow_prism.png
snowpyt/snowflake/ice.png
snowpyt/snowflake/ice_column.png
snowpyt/snowflake/large_rounded.png
snowpyt/snowflake/melt_freeze_crust.png
snowpyt/snowflake/near_surface_faceted.png
snowpyt/snowflake/partly_decomposed.png
snowpyt/snowflake/rain_crust.png
snowpyt/snowflake/recent_snow.png
snowpyt/snowflake/rounded_polycrystals.png
snowpyt/snowflake/rounding_depth_hoar.png
snowpyt/snowflake/rounding_faceted.png
snowpyt/snowflake/rounding_surface_hoar.png
snowpyt/snowflake/sf_dict.py
snowpyt/snowflake/slush.png
snowpyt/snowflake/sun_crust.png
snowpyt/snowflake/surface_hoar.png
snowpyt/snowflake/wind_broken_precip.png
snowpyt/snowflake/wind_packed.png
snowpyt-0.2.2.dist-info/LICENSE.txt
snowpyt-0.2.2.dist-info/METADATA
snowpyt-0.2.2.dist-info/WHEEL
snowpyt-0.2.2.dist-info/top_level.txt
snowpyt-0.2.2.dist-info/RECORD
