Metadata-Version: 2.1
Name: snowpyt
Version: 0.2.2
Summary: A Python project to visualize snowpit
Home-page: https://github.com/ArcticSnow/snowpyt
Author: S. Filhol,G. Sutter
Author-email: simon.filhol@geo.uio.no
License: MIT
Platform: UNKNOWN
Classifier: License :: OSI Approved :: MIT License
Classifier: Programming Language :: Python
Classifier: Programming Language :: Python :: 3
Classifier: Programming Language :: Python :: 3.6
Classifier: Programming Language :: Python :: Implementation :: CPython
Classifier: Programming Language :: Python :: Implementation :: PyPy
Requires-Python: >=3.6.0
Requires-Dist: matplotlib
Requires-Dist: pandas
Requires-Dist: numpy
